odoo/addons/shopinvader_quotation/README.rst
odoo/addons/shopinvader_quotation/__init__.py
odoo/addons/shopinvader_quotation/__manifest__.py
odoo/addons/shopinvader_quotation/data/ir_export_product.xml
odoo/addons/shopinvader_quotation/demo/email_demo.xml
odoo/addons/shopinvader_quotation/demo/notification_demo.xml
odoo/addons/shopinvader_quotation/i18n/fr.po
odoo/addons/shopinvader_quotation/i18n/shopinvader_quotation.pot
odoo/addons/shopinvader_quotation/migrations/14.0.2.0.0/pre-migrate.py
odoo/addons/shopinvader_quotation/models/__init__.py
odoo/addons/shopinvader_quotation/models/product_product.py
odoo/addons/shopinvader_quotation/models/product_template.py
odoo/addons/shopinvader_quotation/models/sale_order.py
odoo/addons/shopinvader_quotation/models/shopinvader_notification.py
odoo/addons/shopinvader_quotation/readme/CONTRIBUTORS.rst
odoo/addons/shopinvader_quotation/readme/CREDITS.rst
odoo/addons/shopinvader_quotation/readme/DESCRIPTION.rst
odoo/addons/shopinvader_quotation/services/__init__.py
odoo/addons/shopinvader_quotation/services/cart.py
odoo/addons/shopinvader_quotation/services/quotation.py
odoo/addons/shopinvader_quotation/static/description/index.html
odoo/addons/shopinvader_quotation/tests/__init__.py
odoo/addons/shopinvader_quotation/tests/test_notification.py
odoo/addons/shopinvader_quotation/tests/test_product.py
odoo/addons/shopinvader_quotation/tests/test_quotation.py
odoo/addons/shopinvader_quotation/tests/test_quotation_download.py
odoo/addons/shopinvader_quotation/views/product_view.xml
odoo/addons/shopinvader_quotation/views/sale_view.xml
odoo14_addon_shopinvader_quotation-14.0.2.3.1.dist-info/METADATA
odoo14_addon_shopinvader_quotation-14.0.2.3.1.dist-info/WHEEL
odoo14_addon_shopinvader_quotation-14.0.2.3.1.dist-info/top_level.txt
odoo14_addon_shopinvader_quotation-14.0.2.3.1.dist-info/RECORD
